goo/__init__.py
goo/goo.py
goo_pm-1.0.0.dist-info/LICENSE
goo_pm-1.0.0.dist-info/METADATA
goo_pm-1.0.0.dist-info/WHEEL
goo_pm-1.0.0.dist-info/entry_points.txt
goo_pm-1.0.0.dist-info/top_level.txt
goo_pm-1.0.0.dist-info/RECORD
