Metadata-Version: 2.1
Name: goo-pm
Version: 1.0.0
Summary: Plugin/dependency manager for Godot
Home-page: https://gitlab.com/nanom_/goo
Author: nanom
License: 0BSD
Keywords: godot package manager plugin plugins gd python
Platform: UNKNOWN
Requires-Python: >=3.0
Requires-Dist: beautifulsoup4
Requires-Dist: click
Requires-Dist: gitpython
Requires-Dist: requests
Requires-Dist: validators
